sparrow_patterns/__init__.py
sparrow_patterns/__main__.py
sparrow_patterns/project.py
sparrow_patterns/utils.py
sparrow_patterns/dependencies/__init__.py
sparrow_patterns/dependencies/dependencies.py
sparrow_patterns/dependencies/templates/pyproject.toml
sparrow_patterns/devcontainer/__init__.py
sparrow_patterns/devcontainer/devcontainer.py
sparrow_patterns/devcontainer/devcontainer_test.py
sparrow_patterns/devcontainer/templates/devcontainer.json
sparrow_patterns/dockerfile/__init__.py
sparrow_patterns/dockerfile/dockerfile_.py
sparrow_patterns/dockerfile/dockerfile_test.py
sparrow_patterns/dockerfile/templates/Dockerfile
sparrow_patterns/github/__init__.py
sparrow_patterns/github/github.py
sparrow_patterns/github/templates/build.yml
sparrow_patterns/gitignore/__init__.py
sparrow_patterns/gitignore/gitignore.py
sparrow_patterns/gitignore/templates/gitignore
sparrow_patterns/makefile/__init__.py
sparrow_patterns/makefile/makefile.py
sparrow_patterns/makefile/templates/Makefile
sparrow_patterns/notebooks/__init__.py
sparrow_patterns/notebooks/notebooks.py
sparrow_patterns/readme/__init__.py
sparrow_patterns/readme/readme.py
sparrow_patterns/readme/templates/README.md
sparrow_patterns/vscode/__init__.py
sparrow_patterns/vscode/vscode.py
sparrow_patterns/vscode/templates/extensions.json
sparrow_patterns/vscode/templates/launch.json
sparrow_patterns/vscode/templates/settings.json
sparrow_patterns-0.8.1.dist-info/licenses/LICENSE
sparrow_patterns-0.8.1.dist-info/METADATA
sparrow_patterns-0.8.1.dist-info/WHEEL
sparrow_patterns-0.8.1.dist-info/entry_points.txt
sparrow_patterns-0.8.1.dist-info/top_level.txt
sparrow_patterns-0.8.1.dist-info/RECORD
