Metadata-Version: 2.4
Name: sparrow-patterns
Version: 0.8.1
Summary: A CLI for updating code patterns in Python projects
Author-email: Sparrow Computing <ben@sparrow.dev>
License: MIT
Requires-Python: >=3.6
License-File: LICENSE
Requires-Dist: fire
Requires-Dist: jinja2
Requires-Dist: python-slugify
Provides-Extra: dev
Requires-Dist: jupyter; extra == "dev"
Requires-Dist: pytest; extra == "dev"
Requires-Dist: pytest-cov; extra == "dev"
Requires-Dist: types-python-slugify; extra == "dev"
Dynamic: license-file
